agenttoolkit/__init__.py
agenttoolkit/api.py
agenttoolkit/configuration.py
agenttoolkit/schema.py
agenttoolkit/tools.py
agenttoolkit/crewai/__init__.py
agenttoolkit/crewai/tool.py
agenttoolkit/crewai/toolkit.py
agenttoolkit/langchain/__init__.py
agenttoolkit/langchain/tool.py
agenttoolkit/langchain/toolkit.py
agenttoolkit/openai/__init__.py
agenttoolkit/openai/tool.py
agenttoolkit/openai/toolkit.py
siren_agent_toolkit-0.1.1.dist-info/METADATA
siren_agent_toolkit-0.1.1.dist-info/WHEEL
siren_agent_toolkit-0.1.1.dist-info/RECORD
