Metadata-Version: 2.4
Name: siren-agent-toolkit
Version: 0.1.1
Summary: Agent toolkit for Siren notification platform
Project-URL: Homepage, https://github.com/KeyValueSoftwareSystems/siren-agent-toolkit
Project-URL: Repository, https://github.com/KeyValueSoftwareSystems/siren-agent-toolkit.git
Project-URL: Documentation, https://docs.trysiren.io
Project-URL: Bug Tracker, https://github.com/KeyValueSoftwareSystems/siren-agent-toolkit/issues
Author-email: Siren <support@trysiren.io>
License: MIT
Keywords: agent,ai,crewai,langchain,notifications,openai,siren,toolkit
Classifier: Development Status :: 4 - Beta
Classifier: Intended Audience :: Developers
Classifier: License :: OSI Approved :: MIT License
Classifier: Programming Language :: Python :: 3
Classifier: Programming Language :: Python :: 3.8
Classifier: Programming Language :: Python :: 3.9
Classifier: Programming Language :: Python :: 3.10
Classifier: Programming Language :: Python :: 3.11
Classifier: Programming Language :: Python :: 3.12
Classifier: Topic :: Communications
Classifier: Topic :: Internet :: WWW/HTTP
Classifier: Topic :: Software Development :: Libraries :: Python Modules
Requires-Python: >=3.8
Requires-Dist: pydantic>=2.0.0
Requires-Dist: trysiren>=0.1.1
Provides-Extra: all
Requires-Dist: crewai-tools>=0.1.0; extra == 'all'
Requires-Dist: crewai>=0.1.0; extra == 'all'
Requires-Dist: langchain-core>=0.1.0; extra == 'all'
Requires-Dist: langchain>=0.1.0; extra == 'all'
Requires-Dist: openai>=1.0.0; extra == 'all'
Provides-Extra: crewai
Requires-Dist: crewai-tools>=0.1.0; extra == 'crewai'
Requires-Dist: crewai>=0.1.0; extra == 'crewai'
Provides-Extra: dev
Requires-Dist: black>=23.0.0; extra == 'dev'
Requires-Dist: flake8>=6.0.0; extra == 'dev'
Requires-Dist: isort>=5.12.0; extra == 'dev'
Requires-Dist: mypy>=1.0.0; extra == 'dev'
Requires-Dist: pytest-asyncio>=0.21.0; extra == 'dev'
Requires-Dist: pytest>=7.0.0; extra == 'dev'
Requires-Dist: python-dotenv>=1.0.0; extra == 'dev'
Provides-Extra: langchain
Requires-Dist: langchain-core>=0.1.0; extra == 'langchain'
Requires-Dist: langchain>=0.1.0; extra == 'langchain'
Provides-Extra: openai
Requires-Dist: openai>=1.0.0; extra == 'openai'
